xmlv/__init__.py
xmlv/preprocessing.py
xmlv/vectorizer.py
xmlv-0.0.2.dist-info/METADATA
xmlv-0.0.2.dist-info/WHEEL
xmlv-0.0.2.dist-info/top_level.txt
xmlv-0.0.2.dist-info/RECORD
